{"version": "2.1.0", "$schema": "https://schemastore.azurewebsites.net/schemas/json/sarif-2.1.0.json", "runs": [{"tool": {"driver": {"name": "STACS", "rules": [{"id": "CredentialPKIPEMRSA", "shortDescription": {"text": "Potential PEM format RSA private key found."}}, {"id": "CredentialNixShadowBlank", "shortDescription": {"text": "User in /etc/passwd has been configured to not require a password."}}, {"id": "CredentialCloudAWSSecretKey", "shortDescription": {"text": "Potential AWS Secret key found."}}], "version": "0.5.1", "downloadUri": "https://www.github.com/stacscan/stacs/", "informationUri": "https://www.github.com/stacscan/stacs/"}}, "results": [{"message": {"text": "Potential PEM format RSA private key found."}, "level": "error", "ruleId": "CredentialPKIPEMRSA", "locations": [{"physicalLocation": {"region": {"byteOffset": 0, "snippet": {"text": "-----BEGIN RSA PRIVATE KEY-----\nMIICXQIBAAKBgQDpMcgC+vp"}, "startLine": 1}, "contextRegion": {"snippet": {"text": "-----BEGIN RSA PRIVATE KEY-----\nMIICXQIBAAKBgQDpMcgC+vpl6+RWpelen2t/Vx6aABg"}}, "artifactLocation": {"uri": "squashfs-root/etc/stunnel/stunnel.pem", "index": 0, "uriBaseId": "STACSROOT"}}}], "suppressions": []}, {"message": {"text": "User in /etc/passwd has been configured to not require a password."}, "level": "error", "ruleId": "CredentialNixShadowBlank", "locations": [{"physicalLocation": {"region": {"byteOffset": 0, "snippet": {"text": "admin::0:0:root:/:/bin/sh\n"}, "startLine": 1}, "contextRegion": {"snippet": {"text": "admin::0:0:root:/:/bin/sh\n"}}, "artifactLocation": {"uri": "squashfs-root/etc/passwd_default", "index": 1, "uriBaseId": "STACSROOT"}}}], "suppressions": []}, {"message": {"text": "User in /etc/passwd has been configured to not require a password."}, "level": "error", "ruleId": "CredentialNixShadowBlank", "locations": [{"physicalLocation": {"region": {"byteOffset": 0, "snippet": {"text": "admin::0:0:root:/:/bin/sh\n"}, "startLine": 1}, "contextRegion": {"snippet": {"text": "admin::0:0:root:/:/bin/sh\n"}}, "artifactLocation": {"uri": "squashfs-root/mnt/flash/config/passwd", "index": 2, "uriBaseId": "STACSROOT"}}}], "suppressions": []}, {"message": {"text": "Potential AWS Secret key found."}, "level": "error", "ruleId": "CredentialCloudAWSSecretKey", "locations": [{"physicalLocation": {"region": {"byteOffset": 202780, "snippet": {"binary": "PT09PT09PT09PT09PT09PT09PT09PT09PT09PT09PT09PT09PT09PQ=="}}, "contextRegion": {"snippet": {"binary": "Z2U9PT09PT09PT09PT09PT09PQA9PT09PT09PT09PT09PT09PT09PT09PT09PT09PT09PT09PT09PT09PT09CgAAAAAlczolZCBbUmVjdl0="}}, "artifactLocation": {"uri": "signalc", "index": 5, "uriBaseId": "STACSROOT"}}}], "suppressions": []}, {"message": {"text": "Potential AWS Secret key found."}, "level": "error", "ruleId": "CredentialCloudAWSSecretKey", "locations": [{"physicalLocation": {"region": {"byteOffset": 202781, "snippet": {"binary": "PT09PT09PT09PT09PT09PT09PT09PT09PT09PT09PT09PT09PT09PQ=="}}, "contextRegion": {"snippet": {"binary": "ZT09PT09PT09PT09PT09PT09AD09PT09PT09PT09PT09PT09PT09PT09PT09PT09PT09PT09PT09PT09PT0KAAAAACVzOiVkIFtSZWN2XSA="}}, "artifactLocation": {"uri": "signalc", "index": 5, "uriBaseId": "STACSROOT"}}}], "suppressions": []}, {"message": {"text": "Potential AWS Secret key found."}, "level": "error", "ruleId": "CredentialCloudAWSSecretKey", "locations": [{"physicalLocation": {"region": {"byteOffset": 202782, "snippet": {"binary": "PT09PT09PT09PT09PT09PT09PT09PT09PT09PT09PT09PT09PT09PQ=="}}, "contextRegion": {"snippet": {"binary": "PT09PT09PT09PT09PT09PT0APT09PT09PT09PT09PT09PT09PT09PT09PT09PT09PT09PT09PT09PT09PQoAAAAAJXM6JWQgW1JlY3ZdIGE="}}, "artifactLocation": {"uri": "signalc", "index": 5, "uriBaseId": "STACSROOT"}}}], "suppressions": []}, {"message": {"text": "Potential AWS Secret key found."}, "level": "error", "ruleId": "CredentialCloudAWSSecretKey", "locations": [{"physicalLocation": {"region": {"byteOffset": 202783, "snippet": {"binary": "PT09PT09PT09PT09PT09PT09PT09PT09PT09PT09PT09PT09PT09PQ=="}}, "contextRegion": {"snippet": {"binary": "PT09PT09PT09PT09PT09PQA9PT09PT09PT09PT09PT09PT09PT09PT09PT09PT09PT09PT09PT09PT09CgAAAAAlczolZCBbUmVjdl0gYXU="}}, "artifactLocation": {"uri": "signalc", "index": 5, "uriBaseId": "STACSROOT"}}}], "suppressions": []}, {"message": {"text": "Potential AWS Secret key found."}, "level": "error", "ruleId": "CredentialCloudAWSSecretKey", "locations": [{"physicalLocation": {"region": {"byteOffset": 203333, "snippet": {"binary": "MTIzNDU2Nzg5MDEyMzQ1Njc4OTAxMjM0NTY3ODkwMTIzNDU2Nzg5MA=="}}, "contextRegion": {"snippet": {"binary": "AAAAZTQ1MzdkZDRhMTVjNGViNS8xMjM0NTY3ODkwMTIzNDU2Nzg5MDEyMzQ1Njc4OTAxMjM0NTY3ODkwLwAAQUtJQUpVWlhPNkVRVllPQUs="}}, "artifactLocation": {"uri": "signalc", "index": 5, "uriBaseId": "STACSROOT"}}}], "suppressions": []}, {"message": {"text": "Potential AWS Secret key found."}, "level": "error", "ruleId": "CredentialCloudAWSSecretKey", "locations": [{"physicalLocation": {"region": {"byteOffset": 206204, "snippet": {"binary": "PT09PT09PT09PT09PT09PT09PT09PT09PT09PT09PT09PT09PT09PQ=="}}, "contextRegion": {"snippet": {"binary": "c10AAAlWYWx1ZSA6IElbJWRdAAA9PT09PT09PT09PT09PT09PT09PT09PT09PT09PT09PT09PT09PT09PT09PT09PT09PQAATG9nIHNvY2s="}}, "artifactLocation": {"uri": "signalc", "index": 5, "uriBaseId": "STACSROOT"}}}], "suppressions": []}, {"message": {"text": "Potential AWS Secret key found."}, "level": "error", "ruleId": "CredentialCloudAWSSecretKey", "locations": [{"physicalLocation": {"region": {"byteOffset": 206205, "snippet": {"binary": "PT09PT09PT09PT09PT09PT09PT09PT09PT09PT09PT09PT09PT09PQ=="}}, "contextRegion": {"snippet": {"binary": "XQAACVZhbHVlIDogSVslZF0AAD09PT09PT09PT09PT09PT09PT09PT09PT09PT09PT09PT09PT09PT09PT09PT09PT09AABMb2cgc29ja2U="}}, "artifactLocation": {"uri": "signalc", "index": 5, "uriBaseId": "STACSROOT"}}}], "suppressions": []}, {"message": {"text": "Potential AWS Secret key found."}, "level": "error", "ruleId": "CredentialCloudAWSSecretKey", "locations": [{"physicalLocation": {"region": {"byteOffset": 206206, "snippet": {"binary": "PT09PT09PT09PT09PT09PT09PT09PT09PT09PT09PT09PT09PT09PQ=="}}, "contextRegion": {"snippet": {"binary": "AAAJVmFsdWUgOiBJWyVkXQAAPT09PT09PT09PT09PT09PT09PT09PT09PT09PT09PT09PT09PT09PT09PT09PT09PT0AAExvZyBzb2NrZXQ="}}, "artifactLocation": {"uri": "signalc", "index": 5, "uriBaseId": "STACSROOT"}}}], "suppressions": []}, {"message": {"text": "Potential AWS Secret key found."}, "level": "error", "ruleId": "CredentialCloudAWSSecretKey", "locations": [{"physicalLocation": {"region": {"byteOffset": 206207, "snippet": {"binary": "PT09PT09PT09PT09PT09PT09PT09PT09PT09PT09PT09PT09PT09PQ=="}}, "contextRegion": {"snippet": {"binary": "AAlWYWx1ZSA6IElbJWRdAAA9PT09PT09PT09PT09PT09PT09PT09PT09PT09PT09PT09PT09PT09PT09PT09PT09PQAATG9nIHNvY2tldCg="}}, "artifactLocation": {"uri": "signalc", "index": 5, "uriBaseId": "STACSROOT"}}}], "suppressions": []}, {"message": {"text": "Potential AWS Secret key found."}, "level": "error", "ruleId": "CredentialCloudAWSSecretKey", "locations": [{"physicalLocation": {"region": {"byteOffset": 206208, "snippet": {"binary": "PT09PT09PT09PT09PT09PT09PT09PT09PT09PT09PT09PT09PT09PQ=="}}, "contextRegion": {"snippet": {"binary": "CVZhbHVlIDogSVslZF0AAD09PT09PT09PT09PT09PT09PT09PT09PT09PT09PT09PT09PT09PT09PT09PT09PT09AABMb2cgc29ja2V0KCk="}}, "artifactLocation": {"uri": "signalc", "index": 5, "uriBaseId": "STACSROOT"}}}], "suppressions": []}, {"message": {"text": "Potential AWS Secret key found."}, "level": "error", "ruleId": "CredentialCloudAWSSecretKey", "locations": [{"physicalLocation": {"region": {"byteOffset": 206209, "snippet": {"binary": "PT09PT09PT09PT09PT09PT09PT09PT09PT09PT09PT09PT09PT09PQ=="}}, "contextRegion": {"snippet": {"binary": "VmFsdWUgOiBJWyVkXQAAPT09PT09PT09PT09PT09PT09PT09PT09PT09PT09PT09PT09PT09PT09PT09PT09PT0AAExvZyBzb2NrZXQoKSA="}}, "artifactLocation": {"uri": "signalc", "index": 5, "uriBaseId": "STACSROOT"}}}], "suppressions": []}, {"message": {"text": "Potential AWS Secret key found."}, "level": "error", "ruleId": "CredentialCloudAWSSecretKey", "locations": [{"physicalLocation": {"region": {"byteOffset": 206210, "snippet": {"binary": "PT09PT09PT09PT09PT09PT09PT09PT09PT09PT09PT09PT09PT09PQ=="}}, "contextRegion": {"snippet": {"binary": "YWx1ZSA6IElbJWRdAAA9PT09PT09PT09PT09PT09PT09PT09PT09PT09PT09PT09PT09PT09PT09PT09PT09PQAATG9nIHNvY2tldCgpIGY="}}, "artifactLocation": {"uri": "signalc", "index": 5, "uriBaseId": "STACSROOT"}}}], "suppressions": []}, {"message": {"text": "Potential AWS Secret key found."}, "level": "error", "ruleId": "CredentialCloudAWSSecretKey", "locations": [{"physicalLocation": {"region": {"byteOffset": 206211, "snippet": {"binary": "PT09PT09PT09PT09PT09PT09PT09PT09PT09PT09PT09PT09PT09PQ=="}}, "contextRegion": {"snippet": {"binary": "bHVlIDogSVslZF0AAD09PT09PT09PT09PT09PT09PT09PT09PT09PT09PT09PT09PT09PT09PT09PT09PT09AABMb2cgc29ja2V0KCkgZmE="}}, "artifactLocation": {"uri": "signalc", "index": 5, "uriBaseId": "STACSROOT"}}}], "suppressions": []}, {"message": {"text": "Potential AWS Secret key found."}, "level": "error", "ruleId": "CredentialCloudAWSSecretKey", "locations": [{"physicalLocation": {"region": {"byteOffset": 206212, "snippet": {"binary": "PT09PT09PT09PT09PT09PT09PT09PT09PT09PT09PT09PT09PT09PQ=="}}, "contextRegion": {"snippet": {"binary": "dWUgOiBJWyVkXQAAPT09PT09PT09PT09PT09PT09PT09PT09PT09PT09PT09PT09PT09PT09PT09PT09PT0AAExvZyBzb2NrZXQoKSBmYWk="}}, "artifactLocation": {"uri": "signalc", "index": 5, "uriBaseId": "STACSROOT"}}}], "suppressions": []}, {"message": {"text": "Potential AWS Secret key found."}, "level": "error", "ruleId": "CredentialCloudAWSSecretKey", "locations": [{"physicalLocation": {"region": {"byteOffset": 206213, "snippet": {"binary": "PT09PT09PT09PT09PT09PT09PT09PT09PT09PT09PT09PT09PT09PQ=="}}, "contextRegion": {"snippet": {"binary": "ZSA6IElbJWRdAAA9PT09PT09PT09PT09PT09PT09PT09PT09PT09PT09PT09PT09PT09PT09PT09PT09PQAATG9nIHNvY2tldCgpIGZhaWw="}}, "artifactLocation": {"uri": "signalc", "index": 5, "uriBaseId": "STACSROOT"}}}], "suppressions": []}, {"message": {"text": "Potential AWS Secret key found."}, "level": "error", "ruleId": "CredentialCloudAWSSecretKey", "locations": [{"physicalLocation": {"region": {"byteOffset": 206214, "snippet": {"binary": "PT09PT09PT09PT09PT09PT09PT09PT09PT09PT09PT09PT09PT09PQ=="}}, "contextRegion": {"snippet": {"binary": "IDogSVslZF0AAD09PT09PT09PT09PT09PT09PT09PT09PT09PT09PT09PT09PT09PT09PT09PT09PT09AABMb2cgc29ja2V0KCkgZmFpbAA="}}, "artifactLocation": {"uri": "signalc", "index": 5, "uriBaseId": "STACSROOT"}}}], "suppressions": []}], "artifacts": [{"location": {"uri": "squashfs-root/etc/stunnel/stunnel.pem", "uriBaseId": "STACSROOT"}, "hashes": {"md5": "d8c6f599bbb3ef5bd42038ecfb88e21c"}}, {"location": {"uri": "squashfs-root/etc/passwd_default", "uriBaseId": "STACSROOT"}, "hashes": {"md5": "ea0c9b2a9197294e85787464cb73689f"}}, {"location": {"uri": "squashfs-root/mnt/flash/config/passwd", "uriBaseId": "STACSROOT"}, "hashes": {"md5": "ea0c9b2a9197294e85787464cb73689f"}}, {"location": {"uri": "squashfs-root/home/mydlink.tgz", "uriBaseId": "STACSROOT"}}, {"location": {"uri": "mydlink", "uriBaseId": "STACSROOT"}, "parentIndex": 3}, {"location": {"uri": "signalc", "uriBaseId": "STACSROOT"}, "parentIndex": 4, "hashes": {"md5": "9ca4eae2032f25b0c0aa9b07392a1054"}}], "originalUriBaseIds": {"STACSROOT": {"uri": "file:///logs/firmware/"}}}]}
